<?xml version="1.0" encoding="UTF-8"?><ssxml version="1.00"><ssxmlquery name="item" version="1.00" account="ULTIMA" profileuserid="3451" profileusercode="Collective Colour XML TEST" profileusername="Collective Colour XML TEST" profileuseremail="matt@collectivecolour.co.uk" request="000001" requestdt="2009-11-06 15:04:43" sessionid="f2e603ff-755e-4a37-835e-daf49316c532"><ssxmlparameters><ssxmlparameter name="itemid">491</ssxmlparameter></ssxmlparameters><item id="491" href="http://www.ultimadisplays.co.uk/ssxml_feed.asp?queryname=item&amp;accesscode=XML1808092003267&amp;itemid=491" ><code>PS500</code><title>Powerspot 500</title><foldername>powerspot_400_ps400/itemid_491</foldername><category1 id="25" href="http://www.ultimadisplays.co.uk/ssxml_feed.asp?queryname=category&amp;accesscode=XML1808092003267&amp;categoryid=25"><name>Lighting</name><path>Pop-Ups &gt; Lighting</path><brand id="0" name="Common" /><fullfoldername>products/pop_ups/lighting/</fullfoldername><parentcategory1 id="13" href="http://www.ultimadisplays.co.uk/ssxml_feed.asp?queryname=category&amp;accesscode=XML1808092003267&amp;categoryid=13" name="Pop-Ups" /></category1><category2 id="89" href="http://www.ultimadisplays.co.uk/ssxml_feed.asp?queryname=category&amp;accesscode=XML1808092003267&amp;categoryid=89"><name>Pop-Up Lighting</name><path>Lighting &gt; Pop-Up Lighting</path><brand id="0" name="Common" /><parentcategory1 id="15" href="http://www.ultimadisplays.co.uk/ssxml_feed.asp?queryname=category&amp;accesscode=XML1808092003267&amp;categoryid=15" name="Lighting" /></category2><category3 id="93" href="http://www.ultimadisplays.co.uk/ssxml_feed.asp?queryname=category&amp;accesscode=XML1808092003267&amp;categoryid=93"><name>Lighting</name><path>Modular Panels and Exhibition Stands &gt; Lighting</path><brand id="0" name="Common" /><parentcategory1 id="37" href="http://www.ultimadisplays.co.uk/ssxml_feed.asp?queryname=category&amp;accesscode=XML1808092003267&amp;categoryid=37" name="Modular Panels and Exhibition Stands" /></category3><category4 id="141" href="http://www.ultimadisplays.co.uk/ssxml_feed.asp?queryname=category&amp;accesscode=XML1808092003267&amp;categoryid=141"><name>Modular Panels and Exhibition stands</name><path>Lighting &gt; Modular Panels and Exhibition stands</path><brand id="0" name="Common" /><parentcategory1 id="15" href="http://www.ultimadisplays.co.uk/ssxml_feed.asp?queryname=category&amp;accesscode=XML1808092003267&amp;categoryid=15" name="Lighting" /></category4><price1 ccy="GBP">0.00</price1><position>1</position><quantity>1</quantity><datetimeupdated>2009-01-12 00:01:01</datetimeupdated><image1 href="http://www.ultimadisplays.co.uk/images/Lighting/Powerspot_500_silver.jpg"></image1><image2 href="http://www.ultimadisplays.co.uk/images/filler.gif"></image2><image3 href="http://www.ultimadisplays.co.uk/images/Lighting/2Light-Kit.jpg"><caption>Example 2 Light Kit </caption></image3><image4 href="http://www.ultimadisplays.co.uk/images/Lighting/Powerspot_500_silver.jpg"></image4><flashtext>price freeze 5 percent</flashtext><flashtextimage1 href="http://www.ultimadisplays.co.uk/images/Price_Freeze_5perc.gif" /><flashtextcode></flashtextcode><flashtextdatetimeupdated>2008-12-08 16:10:33</flashtextdatetimeupdated><language code="EN" name="English" /><attributes count="4"><attribute id="1" name="Description" type="TEXT"><![CDATA[50watt Low voltage spotlight for suitable for panel and pop-up systems]]></attribute><attribute id="2" name="Features" type="TEXT"><![CDATA[50watt MR16 push fit lamp;Available in Silver;3m power lead with UK or Euro plug;450mm gooseneck arm;360 degree rotating head;Supplied with universal fittings enabling the light to be fitted to banners, pop-ups, modular panel systems and Arena 4 Gantry;Supplied individually or as 2 or 4 light kits;&lt;FONT color=#ff0000&gt;2 or 4 light kits include lights, a carry case and a 4 way extension cable&lt;/FONT&gt;]]></attribute><attribute id="8" name="symbol_one" type="TEXT"><![CDATA[Off the shelf]]></attribute><attribute id="9" name="symbol_two" type="TEXT"><![CDATA[1 Year Guarantee]]></attribute></attributes><crosslinks count="1"><link name="" totype="ITEM" toid="42" href="http://www.ultimadisplays.co.uk/ssxml_feed.asp?queryname=item&amp;accesscode=XML1808092003267&amp;itemid=42" /></crosslinks><backlinks count="2"><link name="" fromtype="ITEM" fromid="787" href="http://www.ultimadisplays.co.uk/ssxml_feed.asp?queryname=item&amp;accesscode=XML1808092003267&amp;itemid=787" /><link name="" fromtype="ITEM" fromid="514" href="http://www.ultimadisplays.co.uk/ssxml_feed.asp?queryname=item&amp;accesscode=XML1808092003267&amp;itemid=514" /></backlinks><variants count="3" minprice1="33.25" maxprice1="209.00"><variant id="3680"><code>PS500</code><price1 ccy="GBP">33.25</price1><position>-10</position><quantity>1</quantity><datetimeupdated>2009-01-28 16:56:00</datetimeupdated><attributes count="1"><attribute number="11" name="Finish/Style" type="TEXT"><![CDATA[Single light]]></attribute></attributes></variant><variant id="1940"><code>PS500-K2-101S</code><price1 ccy="GBP">119.00</price1><position>-10</position><quantity>1</quantity><datetimeupdated>2009-01-12 00:01:00</datetimeupdated><attributes count="1"><attribute number="11" name="Finish/Style" type="TEXT"><![CDATA[2 light kit]]></attribute></attributes></variant><variant id="3674"><code>PS500-K4</code><price1 ccy="GBP">209.00</price1><position>-10</position><quantity>1</quantity><datetimeupdated>2009-01-12 00:01:00</datetimeupdated><attributes count="1"><attribute number="11" name="Finish/Style" type="TEXT"><![CDATA[4 light kit]]></attribute></attributes></variant></variants></item>
</ssxmlquery></ssxml>