<?xml version="1.0" encoding="UTF-8"?><ssxml version="1.00"><ssxmlquery name="item" version="1.00" account="ULTIMA" profileuserid="3451" profileusercode="Collective Colour XML TEST" profileusername="Collective Colour XML TEST" profileuseremail="matt@collectivecolour.co.uk" request="000001" requestdt="2009-11-06 15:10:17" sessionid="a1b881f9-6ebb-43ce-895f-39f6c716060f"><ssxmlparameters><ssxmlparameter name="itemid">473</ssxmlparameter></ssxmlparameters><item id="473" href="http://www.ultimadisplays.co.uk/ssxml_feed.asp?queryname=item&amp;accesscode=XML1808092003267&amp;itemid=473" ><code>AS222B</code><title>Jazz - BEING DISCONTINUED</title><foldername>a4_jazz_as222/itemid_473</foldername><category1 id="14" href="http://www.ultimadisplays.co.uk/ssxml_feed.asp?queryname=category&amp;accesscode=XML1808092003267&amp;categoryid=14"><name>Literature Holders</name><path>Literature Holders</path><brand id="0" name="Common" /><fullfoldername>products/literature_holders/</fullfoldername></category1><category2 id="117" href="http://www.ultimadisplays.co.uk/ssxml_feed.asp?queryname=category&amp;accesscode=XML1808092003267&amp;categoryid=117"><name>Literature Holders</name><path>Retail &gt; Literature Holders</path><brand id="0" name="Common" /><parentcategory1 id="11" href="http://www.ultimadisplays.co.uk/ssxml_feed.asp?queryname=category&amp;accesscode=XML1808092003267&amp;categoryid=11" name="Retail" /></category2><category3 id="102" href="http://www.ultimadisplays.co.uk/ssxml_feed.asp?queryname=category&amp;accesscode=XML1808092003267&amp;categoryid=102"><name>Literature Holders</name><path>Modular &gt; Literature Holders</path><brand id="0" name="Common" /><parentcategory1 id="9" href="http://www.ultimadisplays.co.uk/ssxml_feed.asp?queryname=category&amp;accesscode=XML1808092003267&amp;categoryid=9" name="Modular" /></category3><price1 ccy="GBP">105.00</price1><position>1</position><quantity>1</quantity><datetimeupdated>2008-03-10 09:52:10</datetimeupdated><image1 href="http://www.ultimadisplays.co.uk/images/Literature Holders/jazz.jpg"></image1><image4 href="http://www.ultimadisplays.co.uk/images/Literature Holders/jazz.jpg"></image4><document1 href="http://www.ultimadisplays.co.uk/files/User Instructions/Literature Stands/Jazz UI136U-2.pdf"><folder>files/user instructions/literature stands</folder><filename>jazz ui136u-2.pdf</filename><language code="EN" name="English"/></document1><language code="EN" name="English" /><attributes count="4"><attribute id="1" name="Description" type="TEXT"><![CDATA[&lt;STRONG&gt;&lt;FONT color=#ff0000&gt;NB - This product is being discontinued and is only available whilst stocks last.&lt;/FONT&gt;&lt;/STRONG&gt;]]></attribute><attribute id="2" name="Features" type="TEXT"><![CDATA[This clever unique design accommodates landscape or portrait format literature;Splits into 3 pieces;Available in Black (Silver powdercoated colour discontinued);3 pockets;Carry bag included]]></attribute><attribute id="8" name="symbol_one" type="TEXT"><![CDATA[Retail]]></attribute><attribute id="9" name="symbol_two" type="TEXT"><![CDATA[10 Year Guarantee]]></attribute></attributes><variants count="2" minprice1="105.00" maxprice1="105.00"><variant id="2054"><code>AS222B</code><price1 ccy="GBP">105.00</price1><position>-10</position><quantity>1</quantity><datetimeupdated>2008-03-10 09:50:35</datetimeupdated><attributes count="1"><attribute number="9" name="Colour" type="TEXT"><![CDATA[Black]]></attribute></attributes></variant><variant id="2055"><code>AS222S</code><price1 ccy="GBP">105.00</price1><position>-10</position><quantity>1</quantity><datetimeupdated>2008-03-10 09:50:57</datetimeupdated><attributes count="1"><attribute number="9" name="Colour" type="TEXT"><![CDATA[Silver]]></attribute></attributes></variant></variants></item>
</ssxmlquery></ssxml>