<?xml version="1.0" encoding="UTF-8"?><ssxml version="1.00"><ssxmlquery name="item" version="1.00" account="ULTIMA" profileuserid="3451" profileusercode="Collective Colour XML TEST" profileusername="Collective Colour XML TEST" profileuseremail="matt@collectivecolour.co.uk" request="000001" requestdt="2009-11-06 14:10:55" sessionid="471d64cb-cc3c-41ae-9c7f-59f9fb26e9ca"><ssxmlparameters><ssxmlparameter name="itemid">335</ssxmlparameter></ssxmlparameters><item id="335" href="http://www.ultimadisplays.co.uk/ssxml_feed.asp?queryname=item&amp;accesscode=XML1808092003267&amp;itemid=335" ><code>GA105-GA106</code><title>Pole Clips</title><foldername>pole_clip_16mm_ga105/itemid_335</foldername><category1 id="66" href="http://www.ultimadisplays.co.uk/ssxml_feed.asp?queryname=category&amp;accesscode=XML1808092003267&amp;categoryid=66"><name>Modular Panels and Exhibition stands</name><path>Accessories &gt; Modular Panels and Exhibition stands</path><brand id="0" name="Common" /><fullfoldername>products/accessories/modular_panels_and_exhibition_stands/</fullfoldername><parentcategory1 id="41" href="http://www.ultimadisplays.co.uk/ssxml_feed.asp?queryname=category&amp;accesscode=XML1808092003267&amp;categoryid=41" name="Accessories" /></category1><category2 id="157" href="http://www.ultimadisplays.co.uk/ssxml_feed.asp?queryname=category&amp;accesscode=XML1808092003267&amp;categoryid=157"><name>Accessories</name><path>Modular Panels and Exhibition Stands &gt; Accessories</path><brand id="0" name="Common" /><parentcategory1 id="37" href="http://www.ultimadisplays.co.uk/ssxml_feed.asp?queryname=category&amp;accesscode=XML1808092003267&amp;categoryid=37" name="Modular Panels and Exhibition Stands" /></category2><price1 ccy="GBP">0.00</price1><position>1</position><quantity>1</quantity><datetimeupdated>2009-01-12 00:01:00</datetimeupdated><image1 href="http://www.ultimadisplays.co.uk/images/Accessories/Pole_Clips.jpg"></image1><image4 href="http://www.ultimadisplays.co.uk/images/Accessories/Pole_Clips.jpg"></image4><language code="EN" name="English" /><attributes count="3"><attribute id="2" name="Features" type="TEXT"><![CDATA[Available in black or grey;Supplied in packs of 10;Choice of two sizes, suitable for 16mm or 25mm dia poles;Not suitable for Matrix panels]]></attribute><attribute id="8" name="symbol_one" type="TEXT"><![CDATA[Off the shelf]]></attribute><attribute id="9" name="symbol_two" type="TEXT"><![CDATA[10 Year Guarantee]]></attribute></attributes><backlinks count="8"><link name="" fromtype="ITEM" fromid="317" href="http://www.ultimadisplays.co.uk/ssxml_feed.asp?queryname=item&amp;accesscode=XML1808092003267&amp;itemid=317" /><link name="" fromtype="ITEM" fromid="701" href="http://www.ultimadisplays.co.uk/ssxml_feed.asp?queryname=item&amp;accesscode=XML1808092003267&amp;itemid=701" /><link name="" fromtype="ITEM" fromid="289" href="http://www.ultimadisplays.co.uk/ssxml_feed.asp?queryname=item&amp;accesscode=XML1808092003267&amp;itemid=289" /><link name="" fromtype="ITEM" fromid="569" href="http://www.ultimadisplays.co.uk/ssxml_feed.asp?queryname=item&amp;accesscode=XML1808092003267&amp;itemid=569" /><link name="" fromtype="ITEM" fromid="275" href="http://www.ultimadisplays.co.uk/ssxml_feed.asp?queryname=item&amp;accesscode=XML1808092003267&amp;itemid=275" /><link name="" fromtype="ITEM" fromid="548" href="http://www.ultimadisplays.co.uk/ssxml_feed.asp?queryname=item&amp;accesscode=XML1808092003267&amp;itemid=548" /><link name="" fromtype="ITEM" fromid="547" href="http://www.ultimadisplays.co.uk/ssxml_feed.asp?queryname=item&amp;accesscode=XML1808092003267&amp;itemid=547" /><link name="" fromtype="ITEM" fromid="281" href="http://www.ultimadisplays.co.uk/ssxml_feed.asp?queryname=item&amp;accesscode=XML1808092003267&amp;itemid=281" /></backlinks><variants count="4" minprice1="5.00" maxprice1="5.00"><variant id="1547"><code>GA105B</code><price1 ccy="GBP">5.00</price1><position>0</position><quantity>1</quantity><datetimeupdated>2009-01-12 00:01:00</datetimeupdated><attributes count="2"><attribute number="11" name="Finish/Style" type="TEXT"><![CDATA[Black]]></attribute><attribute number="14" name="Description" type="TEXT"><![CDATA[16mm Pole clip]]></attribute></attributes></variant><variant id="2558"><code>GA105G</code><price1 ccy="GBP">5.00</price1><position>0</position><quantity>1</quantity><datetimeupdated>2009-01-12 00:01:00</datetimeupdated><attributes count="2"><attribute number="11" name="Finish/Style" type="TEXT"><![CDATA[Grey]]></attribute><attribute number="14" name="Description" type="TEXT"><![CDATA[16mm Pole clip]]></attribute></attributes></variant><variant id="1548"><code>GA106B</code><price1 ccy="GBP">5.00</price1><position>0</position><quantity>1</quantity><datetimeupdated>2009-01-12 00:01:00</datetimeupdated><attributes count="2"><attribute number="11" name="Finish/Style" type="TEXT"><![CDATA[Black]]></attribute><attribute number="14" name="Description" type="TEXT"><![CDATA[25mm Pole clip]]></attribute></attributes></variant><variant id="2559"><code>GA106G</code><price1 ccy="GBP">5.00</price1><position>0</position><quantity>1</quantity><datetimeupdated>2009-01-12 00:01:00</datetimeupdated><attributes count="2"><attribute number="11" name="Finish/Style" type="TEXT"><![CDATA[Grey]]></attribute><attribute number="14" name="Description" type="TEXT"><![CDATA[25mm Pole clip]]></attribute></attributes></variant></variants></item>
</ssxmlquery></ssxml>