<?xml version="1.0" encoding="UTF-8"?><ssxml version="1.00"><ssxmlquery name="item" version="1.00" account="ULTIMA" profileuserid="3451" profileusercode="Collective Colour XML TEST" profileusername="Collective Colour XML TEST" profileuseremail="matt@collectivecolour.co.uk" request="000001" requestdt="2009-11-06 15:05:38" sessionid="408ad3e7-a6bd-4e96-a356-ce12bbde05c3"><ssxmlparameters><ssxmlparameter name="itemid">887</ssxmlparameter></ssxmlparameters><item id="887" href="http://www.ultimadisplays.co.uk/ssxml_feed.asp?queryname=item&amp;accesscode=XML1808092003267&amp;itemid=887" ><code>LN-SL-1000x750</code><title>Linear Slatwall Panel</title><foldername>linear_slatwall_panel_ln_sl_1000x750/itemid_887</foldername><category1 id="196" href="http://www.ultimadisplays.co.uk/ssxml_feed.asp?queryname=category&amp;accesscode=XML1808092003267&amp;categoryid=196"><name>Linear Accessories</name><path>Linear &gt; Linear Accessories</path><brand id="0" name="Common" /><fullfoldername>products/linear/linear_accessories/</fullfoldername><parentcategory1 id="195" href="http://www.ultimadisplays.co.uk/ssxml_feed.asp?queryname=category&amp;accesscode=XML1808092003267&amp;categoryid=195" name="Linear" /></category1><price1 ccy="GBP">116.00</price1><position>1</position><quantity>1</quantity><datetimeupdated>2007-03-15 14:25:22</datetimeupdated><image1 href="http://www.ultimadisplays.co.uk/images/Linear/Linear_Slatwall_andhook.jpg"></image1><image4 href="http://www.ultimadisplays.co.uk/images/Linear/Linear_Slatwall_andhook.jpg"></image4><language code="EN" name="English" /><attributes count="4"><attribute id="1" name="Description" type="TEXT"><![CDATA[Slatwall panel accessory for Linear kits]]></attribute><attribute id="2" name="Features" type="TEXT"><![CDATA[1000mm (h) x 750mm (w);White finish]]></attribute><attribute id="8" name="symbol_one" type="TEXT"><![CDATA[Modular]]></attribute><attribute id="9" name="symbol_two" type="TEXT"><![CDATA[10 Year Guarantee]]></attribute></attributes><crosslinks count="2"><link name="" totype="ITEM" toid="889" href="http://www.ultimadisplays.co.uk/ssxml_feed.asp?queryname=item&amp;accesscode=XML1808092003267&amp;itemid=889" /><link name="" totype="ITEM" toid="330" href="http://www.ultimadisplays.co.uk/ssxml_feed.asp?queryname=item&amp;accesscode=XML1808092003267&amp;itemid=330" /></crosslinks></item>
</ssxmlquery></ssxml>