<?xml version="1.0" encoding="UTF-8"?><ssxml version="1.00"><ssxmlquery name="item" version="1.00" account="ULTIMA" profileuserid="3451" profileusercode="Collective Colour XML TEST" profileusername="Collective Colour XML TEST" profileuseremail="matt@collectivecolour.co.uk" request="000001" requestdt="2009-11-06 14:10:05" sessionid="d3294193-f010-4c7a-88b9-e9223fc7aab3"><ssxmlparameters><ssxmlparameter name="itemid">726</ssxmlparameter></ssxmlparameters><item id="726" href="http://www.ultimadisplays.co.uk/ssxml_feed.asp?queryname=item&amp;accesscode=XML1808092003267&amp;itemid=726" ><code>US200</code><title>4 Way Extension Cable</title><foldername>4_way_extension_cable_us200/itemid_726</foldername><category1 id="165" href="http://www.ultimadisplays.co.uk/ssxml_feed.asp?queryname=category&amp;accesscode=XML1808092003267&amp;categoryid=165"><name>Accessories</name><path>Lighting &gt; Accessories</path><brand id="0" name="Common" /><fullfoldername>products/lighting/accessories/</fullfoldername><parentcategory1 id="15" href="http://www.ultimadisplays.co.uk/ssxml_feed.asp?queryname=category&amp;accesscode=XML1808092003267&amp;categoryid=15" name="Lighting" /></category1><category2 id="26" href="http://www.ultimadisplays.co.uk/ssxml_feed.asp?queryname=category&amp;accesscode=XML1808092003267&amp;categoryid=26"><name>Lighting</name><path>Accessories &gt; Lighting</path><brand id="0" name="Common" /><parentcategory1 id="41" href="http://www.ultimadisplays.co.uk/ssxml_feed.asp?queryname=category&amp;accesscode=XML1808092003267&amp;categoryid=41" name="Accessories" /></category2><price1 ccy="GBP">11.00</price1><position>1</position><quantity>1</quantity><datetimeupdated>2009-01-12 00:01:01</datetimeupdated><image1 href="http://www.ultimadisplays.co.uk/images/Accessories/4_way_extension_lead.jpg"></image1><image4 href="http://www.ultimadisplays.co.uk/images/Accessories/4_way_extension_lead.jpg"></image4><language code="EN" name="English" /><attributes count="3"><attribute id="2" name="Features" type="TEXT"><![CDATA[4 sockets;3m approx cable length;3 pin UK plug]]></attribute><attribute id="8" name="symbol_one" type="TEXT"><![CDATA[Off the shelf]]></attribute><attribute id="9" name="symbol_two" type="TEXT"><![CDATA[1 Year Guarantee]]></attribute></attributes></item>
</ssxmlquery></ssxml>