<?xml version="1.0" encoding="UTF-8"?><ssxml version="1.00"><ssxmlquery name="item" version="1.00" account="ULTIMA" profileuserid="3451" profileusercode="Collective Colour XML TEST" profileusername="Collective Colour XML TEST" profileuseremail="matt@collectivecolour.co.uk" request="000001" requestdt="2009-11-06 14:12:17" sessionid="5aa2a39b-7da7-4b32-bbad-17081a5e8e60"><ssxmlparameters><ssxmlparameter name="itemid">852</ssxmlparameter></ssxmlparameters><item id="852" href="http://www.ultimadisplays.co.uk/ssxml_feed.asp?queryname=item&amp;accesscode=XML1808092003267&amp;itemid=852" ><code>WH321C</code><title>Barracuda **NEW MODEL**</title><foldername>new_barracuda_wh321c/itemid_852</foldername><category1 id="21" href="http://www.ultimadisplays.co.uk/ssxml_feed.asp?queryname=category&amp;accesscode=XML1808092003267&amp;categoryid=21"><name>Roller Banners</name><path>Banner Stands &gt; Roller Banners</path><brand id="0" name="Common" /><fullfoldername>products/banner_stands/roller-banners/</fullfoldername><parentcategory1 id="3" href="http://www.ultimadisplays.co.uk/ssxml_feed.asp?queryname=category&amp;accesscode=XML1808092003267&amp;categoryid=3" name="Banner Stands" /></category1><price1 ccy="GBP">0.00</price1><position>1</position><quantity>1</quantity><datetimeupdated>2009-01-12 00:01:01</datetimeupdated><image1 href="http://www.ultimadisplays.co.uk/images/Banner Stands/Barracuda_new.jpg"></image1><image2 href="http://www.ultimadisplays.co.uk/images/Banner Stands/Barracuda_base_new.jpg"></image2><image4 href="http://www.ultimadisplays.co.uk/images/Banner Stands/Barracuda_new.jpg"></image4><document1 href="http://www.ultimadisplays.co.uk/files/User Instructions/Banner Stands/NEW_Barracuda_OCT06.pdf"><folder>files/user instructions/banner stands</folder><filename>new_barracuda_oct06.pdf</filename><language code="EN" name="English"/></document1><flashtext>price freeze 5 percent</flashtext><flashtextimage1 href="http://www.ultimadisplays.co.uk/images/Price_Freeze_5perc.gif" /><flashtextcode></flashtextcode><flashtextdatetimeupdated>2008-12-05 15:12:42</flashtextdatetimeupdated><language code="EN" name="English" /><attributes count="4"><attribute id="1" name="Description" type="TEXT"><![CDATA[Stylish design and proven reliability makes Barracuda our most popular quality banner stand. Barracuda is the most feature-rich single-sided roller banner available and has been specially designed for maximum convenience and ease of use.]]></attribute><attribute id="2" name="Features" type="TEXT"><![CDATA[2130mm max high x 800 or 1000mm wide visible graphic area (add 300mm to allow for  roller mechanism;Available in anodised silver;Charcoal grey end caps;Internal graphic housing designed to accommodate graphic media up to 450 microns thick&lt;FONT color=#ff0000&gt;*&lt;/FONT&gt;;Universal Grippa/Self adhesive top rail;Secure slide in graphic system;Ratchet tensioner;Twist &amp; Lock telescopic pole;Supplied with quality foam padded carry bag;&lt;FONT color=#ff0000&gt;*Please test your substrate suitability before use&lt;/FONT&gt;]]></attribute><attribute id="8" name="symbol_one" type="TEXT"><![CDATA[Off the shelf]]></attribute><attribute id="9" name="symbol_two" type="TEXT"><![CDATA[10 Year Guarantee]]></attribute></attributes><crosslinks count="7"><link name="" totype="ITEM" toid="894" href="http://www.ultimadisplays.co.uk/ssxml_feed.asp?queryname=item&amp;accesscode=XML1808092003267&amp;itemid=894" /><link name="" totype="ITEM" toid="498" href="http://www.ultimadisplays.co.uk/ssxml_feed.asp?queryname=item&amp;accesscode=XML1808092003267&amp;itemid=498" /><link name="" totype="ITEM" toid="917" href="http://www.ultimadisplays.co.uk/ssxml_feed.asp?queryname=item&amp;accesscode=XML1808092003267&amp;itemid=917" /><link name="" totype="ITEM" toid="980" href="http://www.ultimadisplays.co.uk/ssxml_feed.asp?queryname=item&amp;accesscode=XML1808092003267&amp;itemid=980" /><link name="" totype="ITEM" toid="895" href="http://www.ultimadisplays.co.uk/ssxml_feed.asp?queryname=item&amp;accesscode=XML1808092003267&amp;itemid=895" /><link name="" totype="ITEM" toid="897" href="http://www.ultimadisplays.co.uk/ssxml_feed.asp?queryname=item&amp;accesscode=XML1808092003267&amp;itemid=897" /><link name="" totype="ITEM" toid="893" href="http://www.ultimadisplays.co.uk/ssxml_feed.asp?queryname=item&amp;accesscode=XML1808092003267&amp;itemid=893" /></crosslinks><variants count="2" minprice1="109.25" maxprice1="118.75"><variant id="4592"><code>WH321C-1000A</code><price1 ccy="GBP">118.75</price1><position>1</position><quantity>1</quantity><datetimeupdated>2009-01-28 16:21:44</datetimeupdated><attributes count="1"><attribute number="5" name="Width mm" type="INT"><![CDATA[1000]]></attribute></attributes></variant><variant id="4591"><code>WH321C-800A</code><price1 ccy="GBP">109.25</price1><position>1</position><quantity>1</quantity><datetimeupdated>2009-01-28 16:21:15</datetimeupdated><attributes count="1"><attribute number="5" name="Width mm" type="INT"><![CDATA[800]]></attribute></attributes></variant></variants></item>
</ssxmlquery></ssxml>